boundbox2d/__init__.py
boundbox2d/boundbox2d.py
boundbox2d-1.0.0.dist-info/METADATA
boundbox2d-1.0.0.dist-info/WHEEL
boundbox2d-1.0.0.dist-info/top_level.txt
boundbox2d-1.0.0.dist-info/RECORD
