Metadata-Version: 2.1
Name: boundbox2d
Version: 1.0.0
Summary: Bound Box 2D
Home-page: https://github.com/duducosmos/boundbox2d
Author: Eduardo S. Pereira
Author-email: pereira.somoza@gmail.com
License: Apache License 2.0
Platform: UNKNOWN
Requires-Dist: numpy
